gimmebio.hiveplots-0.5.0-py3.6-nspkg.pth
gimmebio/hiveplots/__init__.py
gimmebio/hiveplots/geometry.py
gimmebio/hiveplots/hiveplots.py
gimmebio/hiveplots/colors/__init__.py
gimmebio/hiveplots/colors/color_tree.py
gimmebio/hiveplots/colors/parse_mpa_to_colors.py
gimmebio.hiveplots-0.5.0.dist-info/METADATA
gimmebio.hiveplots-0.5.0.dist-info/RECORD
gimmebio.hiveplots-0.5.0.dist-info/WHEEL
gimmebio.hiveplots-0.5.0.dist-info/namespace_packages.txt
gimmebio.hiveplots-0.5.0.dist-info/top_level.txt
